MySerializer.py
json_helper.py
serialization_helper.py
xml_helper.py
object_serialization-0.1.2.dist-info/METADATA
object_serialization-0.1.2.dist-info/WHEEL
object_serialization-0.1.2.dist-info/top_level.txt
object_serialization-0.1.2.dist-info/RECORD
