Metadata-Version: 2.1
Name: object-serialization
Version: 0.1.2
Summary: Python serialization package for python objects
